mogit/__init__.py
mogit/cli.py
mogit/ignorefile.py
mogit/objs.py
mogit/repo.py
mogit/sign.py
mogit-1.0.0.dist-info/LICENSE
mogit-1.0.0.dist-info/METADATA
mogit-1.0.0.dist-info/WHEEL
mogit-1.0.0.dist-info/entry_points.txt
mogit-1.0.0.dist-info/top_level.txt
mogit-1.0.0.dist-info/RECORD
