Metadata-Version: 2.1
Name: mogit
Version: 1.0.0
Summary: 一个轻量级的分布式版本控制系统
Home-page: UNKNOWN
Author: MoYan
Author-email: moyan@moyanjdc.top
License: UNKNOWN
Platform: UNKNOWN
Classifier: Development Status :: 3 - Alpha
Classifier: Intended Audience :: Developers
Classifier: License :: OSI Approved :: MIT License
Classifier: Programming Language :: Python :: 3
Classifier: Programming Language :: Python :: 3.7
Classifier: Programming Language :: Python :: 3.8
Classifier: Programming Language :: Python :: 3.9
Classifier: Environment :: Console
Classifier: Programming Language :: Python :: 3.10
License-File: LICENSE
Requires-Dist: click (==8.1.7)
Requires-Dist: rsa (==4.9)
